pydantic_rng/__init__.py
pydantic_rng/lib.py
pydantic_rng/py.typed
pydantic_rng-0.1.6.dist-info/WHEEL
pydantic_rng-0.1.6.dist-info/METADATA
pydantic_rng-0.1.6.dist-info/RECORD
