Metadata-Version: 2.3
Name: pydantic-rng
Version: 0.1.6
Summary: Generate randomized instances of pydantic classes for testing
Author: Nick Anthony
Author-email: Nick Anthony <nanthony007@gmail.com>
Requires-Dist: pydantic>=2.0
Requires-Python: >=3.12
